[
    {
        "name": "Kastoria, Greece - Aristoteles",
        "code": "KSO"
    },
    {
        "name": "Naxos, Greece - Naxos",
        "code": "JNX"
    },
    {
        "name": "Milos, Greece - Milos",
        "code": "MLO"
    },
    {
        "name": "Ikaria Island, Greece - Ikaria Airport",
        "code": "JIK"
    },
    {
        "name": "Leros, Greece - Leros",
        "code": "LRS"
    },
    {
        "name": "Patras, Greece",
        "code": "GPA"
    },
    {
        "name": "Kithira, Greece - Kithira Airport",
        "code": "KIT"
    },
    {
        "name": "Sitia, Greece - Sitia",
        "code": "JSH"
    },
    {
        "name": "Kalymnos, Greece - Kalymnos Island National Airport",
        "code": "JKL"
    },
    {
        "name": "Syros Island, Greece - Syros Island Airport",
        "code": "JSY"
    },
    {
        "name": "Astypalaia Island, Greece - Astypalaia Airport",
        "code": "JTY"
    },
    {
        "name": "Skiros, Greece - Skiros",
        "code": "SKU"
    },
    {
        "name": "Ioannina, Greece - Ioannina",
        "code": "IOA"
    },
    {
        "name": "Kozani, Greece - Philippos",
        "code": "KZI"
    },
    {
        "name": "Kasos Island, Greece - Kasos Island Airport",
        "code": "KSJ"
    },
    {
        "name": "Kastelorizo, Greece - Kastelorizo Airport",
        "code": "KZS"
    },
    {
        "name": "Volos, Greece",
        "code": "VOL"
    },
    {
        "name": "Andravida, Greece - Andravida Airport",
        "code": "PYR"
    },
    {
        "name": "Agrinion, Greece - Agrinion Airport",
        "code": "AGQ"
    },
    {
        "name": "Athens, Greece - Athen Helenikon Airport",
        "code": "HEW"
    },
    {
        "name": "Porto Cheli, Greece - Porto Cheli Airport",
        "code": "PKH"
    },
    {
        "name": "Larisa, Greece - Larisa Airport",
        "code": "LRA"
    },
    {
        "name": "Sparti, Greece - Sparti Airport",
        "code": "SPJ"
    },
    {
        "name": "Kefalonia, Greece - Argostoli",
        "code": "EFL"
    },
    {
        "name": "Thessaloniki, Greece - Makedonia",
        "code": "SKG"
    },
    {
        "name": "Heraklion, Greece - N. Kazantzakis",
        "code": "HER"
    },
    {
        "name": "Rhodes Is., Greece - Diagoras",
        "code": "RHO"
    },
    {
        "name": "Kerkyra, Greece - I Kapodistrias",
        "code": "CFU"
    },
    {
        "name": "Kos, Greece - Kos",
        "code": "KGS"
    },
    {
        "name": "Fira, Greece - Santorini Airport",
        "code": "JTR"
    },
    {
        "name": "Chania, Greece - Chania-Souda",
        "code": "CHQ"
    },
    {
        "name": "Zakinthos, Greece - Zakinthos",
        "code": "ZTH"
    },
    {
        "name": "Mykonos, Greece - Mikonos",
        "code": "JMK"
    },
    {
        "name": "Mitilini, Greece - Mytilene",
        "code": "MJT"
    },
    {
        "name": "Athens, Greece - Eleftherios Venizelos Intl Airport",
        "code": "ATH"
    },
    {
        "name": "Chios, Greece - Chios",
        "code": "JKH"
    },
    {
        "name": "Samos Island, Greece - Samos",
        "code": "SMI"
    },
    {
        "name": "Preveza, Greece - Aktion",
        "code": "PVK"
    },
    {
        "name": "Kavala, Greece - Megas Alexandros",
        "code": "KVA"
    },
    {
        "name": "Skiathos, Greece - Skiathos",
        "code": "JSI"
    },
    {
        "name": "Paros, Greece - Paros",
        "code": "PAS"
    },
    {
        "name": "Kalamata, Greece",
        "code": "KLX"
    },
    {
        "name": "Alexandroupolis, Greece - Demokritos",
        "code": "AXD"
    },
    {
        "name": "Limnos, Greece - Limnos",
        "code": "LXS"
    },
    {
        "name": "Karpathos, Greece - Karpathos Airport",
        "code": "AOK"
    }
]