[
    {
        "name": "Apia, Samoa - Faleolo",
        "code": "APW"
    },
    {
        "name": "Pago Pago, American Samoa - Tafuna/Pago Pago International Airport",
        "code": "PPG"
    },
    {
        "name": "Apia, Samoa",
        "code": "FGI"
    },
    {
        "name": "Ofu Village, American Samoa - Ofu Village Airport",
        "code": "OFU"
    },
    {
        "name": "Asau, Samoa - Asau Airport",
        "code": "AAU"
    },
    {
        "name": "Fitiuta Village, American Samoa - Fitiuta Airport",
        "code": "FTI"
    },
    {
        "name": "Maota, Samoa - Maota Airport",
        "code": "MXS"
    }
]